odoo/addons/ssi_currency_mixin/README.rst
odoo/addons/ssi_currency_mixin/__init__.py
odoo/addons/ssi_currency_mixin/__manifest__.py
odoo/addons/ssi_currency_mixin/models/__init__.py
odoo/addons/ssi_currency_mixin/models/mixin_currency.py
odoo/addons/ssi_currency_mixin/static/description/icon.png
odoo14_addon_ssi_currency_mixin-14.0.1.2.0.dist-info/METADATA
odoo14_addon_ssi_currency_mixin-14.0.1.2.0.dist-info/WHEEL
odoo14_addon_ssi_currency_mixin-14.0.1.2.0.dist-info/top_level.txt
odoo14_addon_ssi_currency_mixin-14.0.1.2.0.dist-info/RECORD
